Metadata-Version: 2.1
Name: somas-jose
Version: 0.0.1
Summary: Repositorio para testes
Author: Jose Eduardo
Author-email: josedumoura@gmail.com
License: MIT License
Keywords: somas jose
License-File: LICENSE
